rcounting/__init__.py
rcounting/analysis.py
rcounting/configure_logging.py
rcounting/ftf.py
rcounting/graph_tools.py
rcounting/io.py
rcounting/models.py
rcounting/parsing.py
rcounting/plots.py
rcounting/reddit_interface.py
rcounting/thread_directory.py
rcounting/thread_navigation.py
rcounting/units.py
rcounting/utils.py
rcounting/counters/__init__.py
rcounting/counters/aliases.txt
rcounting/counters/counters.py
rcounting/scripts/__init__.py
rcounting/scripts/cli.py
rcounting/scripts/ftf.py
rcounting/scripts/log_all_side_threads.py
rcounting/scripts/log_thread.py
rcounting/scripts/update_thread_directory.py
rcounting/scripts/validate.py
rcounting/scripts/weekly_side_thread_stats.py
rcounting/side_threads/__init__.py
rcounting/side_threads/base_n_threads.py
rcounting/side_threads/dfa.py
rcounting/side_threads/elements.txt
rcounting/side_threads/forms.py
rcounting/side_threads/rules.py
rcounting/side_threads/side_threads.ini
rcounting/side_threads/side_threads.py
rcounting/side_threads/thread_list.py
rcounting/side_threads/us_states.txt
rcounting/side_threads/validate_form.py
rcounting-0.7.dist-info/licenses/LICENSE.md
rcounting-0.7.dist-info/METADATA
rcounting-0.7.dist-info/WHEEL
rcounting-0.7.dist-info/entry_points.txt
rcounting-0.7.dist-info/top_level.txt
rcounting-0.7.dist-info/RECORD
