Metadata-Version: 2.4
Name: rcounting
Version: 0.7
Summary: A collection of tools for working with comments made on www.reddit.com/r/counting
Author-email: CutOnBumInBand <cutonbuminband@gmail.com>
License-Expression: GPL-3.0-or-later
Project-URL: repository, https://github.com/cutonbuminband/rcounting
Classifier: Programming Language :: Python :: 3
Classifier: Development Status :: 3 - Alpha
Classifier: Operating System :: OS Independent
Requires-Python: >=3.10
License-File: LICENSE.md
Requires-Dist: click>=8.1.7
Requires-Dist: fuzzywuzzy>=0.18.0
Requires-Dist: levenshtein>=0.27.1
Requires-Dist: pandas>=2.2.3
Requires-Dist: praw>=7.8.1
Requires-Dist: scipy>=1.14.1
Provides-Extra: analysis
Requires-Dist: jupyter>=1.1.1; extra == "analysis"
Requires-Dist: matplotlib>=3.9.2; extra == "analysis"
Requires-Dist: networkx>=3.4.2; extra == "analysis"
Requires-Dist: scikit-learn>=1.7.1; extra == "analysis"
Requires-Dist: seaborn>=0.13.2; extra == "analysis"
Requires-Dist: tabulate>=0.9.0; extra == "analysis"
Provides-Extra: dev
Requires-Dist: ruff>=0.7.3; extra == "dev"
Requires-Dist: uv>=0.5.1; extra == "dev"
Dynamic: license-file
